bstokenizer/TokenType.py
bstokenizer/__init__.py
bstokenizer/cli.py
bstokenizer/mapconvert.py
bstokenizer/maptokenizer.py
bstokenizer/replaytokenizer.py
bstokenizer/version.py
bstokenizer/heck/__init__.py
bstokenizer/heck/customDataHandler.py
bstokenizer/heck/utils.py
bstokenizer/tests/__init__.py
bstokenizer/tests/test.py
bstokenizer-0.1.3.dist-info/METADATA
bstokenizer-0.1.3.dist-info/WHEEL
bstokenizer-0.1.3.dist-info/entry_points.txt
bstokenizer-0.1.3.dist-info/top_level.txt
bstokenizer-0.1.3.dist-info/RECORD
