Metadata-Version: 2.4
Name: bstokenizer
Version: 0.1.3
Summary: A library for tokenizing Beat Saber maps and replays
Home-page: https://github.com/CodeSoftGit/bstokenizer
Author: CodeSoft
Author-email: hello@mail.codesoft.is-a.dev
Classifier: Programming Language :: Python :: 3
Classifier: License :: OSI Approved :: MIT License
Classifier: Operating System :: OS Independent
Requires-Python: >=3.6
Requires-Dist: py-bsor
Provides-Extra: dev
Requires-Dist: pytest>=6.0; extra == "dev"
Requires-Dist: pytest-cov; extra == "dev"
Requires-Dist: black; extra == "dev"
Dynamic: author
Dynamic: author-email
Dynamic: classifier
Dynamic: description
Dynamic: description-content-type
Dynamic: home-page
Dynamic: provides-extra
Dynamic: requires-dist
Dynamic: requires-python
Dynamic: summary
